interact/__init__.py
interact/constants.py
interact/md_system.py
interact/selections.py
interact/core/__init__.py
interact/core/data.py
interact/core/fileio.py
interact/core/geometry.py
interact/core/helpers.py
interact/core/sssr.py
interact/core/sybyl.py
interact/core/topology_base.py
interact/core/topology_dataframe.py
interact/core/topology_series.py
interact/data/element_data.csv
interact/data/residue_data.csv
interact/interactions/__init__.py
interact/interactions/charged.py
interact/interactions/halogen.py
interact/interactions/hbonds.py
interact/interactions/hydrofobic.py
interact/interactions/utils.py
tests/__init__.py
tests/__main__.py
tests/module/__init__.py
tests/module/module_evaluators_test.py
tests/module/module_geometry_test.py
tests/module/module_load_topology_test.py
tests/module/module_topology_dataframe_test.py
tests/module/module_topology_distmat_test.py
tests/module/module_topology_quickselector_test.py
tests/module/module_topology_series_test.py
tests/module/test_data.py
tests/module/unittest_baseclass.py
mdinteract-0.1.dist-info/LICENSE
mdinteract-0.1.dist-info/METADATA
mdinteract-0.1.dist-info/WHEEL
mdinteract-0.1.dist-info/top_level.txt
mdinteract-0.1.dist-info/zip-safe
mdinteract-0.1.dist-info/RECORD
